llama_index/py.typed
llama_index/vector_stores/volcengine_mysql/__init__.py
llama_index/vector_stores/volcengine_mysql/base.py
llama_index_vector_stores_volcengine_mysql-0.2.0.dist-info/METADATA
llama_index_vector_stores_volcengine_mysql-0.2.0.dist-info/WHEEL
llama_index_vector_stores_volcengine_mysql-0.2.0.dist-info/RECORD
