Metadata-Version: 2.4
Name: llama-index-vector-stores-volcengine-mysql
Version: 0.2.0
Summary: llama-index vector_stores Volcengine MySQL integration
Author-email: Siyu Chen <fishmage33@gmail.com>
License-Expression: MIT
Requires-Python: <4.0,>=3.9
Requires-Dist: aiomysql>=0.2.0
Requires-Dist: llama-index-core<0.15,>=0.13.0
Requires-Dist: pymysql<2,>=1.1.1
Requires-Dist: sqlalchemy<2.1,>=2.0
